parabolic/__about__.py
parabolic/__init__.py
parabolic/time_steppers.py
parabolic-0.1.2.dist-info/DESCRIPTION.rst
parabolic-0.1.2.dist-info/METADATA
parabolic-0.1.2.dist-info/RECORD
parabolic-0.1.2.dist-info/WHEEL
parabolic-0.1.2.dist-info/metadata.json
parabolic-0.1.2.dist-info/top_level.txt
