Metadata-Version: 2.0
Name: parabolic
Version: 0.1.2
Summary: Time-steppers for parabolic PDEs
Home-page: https://github.com/nschloe/parabolic
Author: Nico Schlömer
Author-email: nico.schloemer@gmail.com
License: License :: OSI Approved :: MIT License
Download-URL: https://github.com/nschloe/parabolic/releases
Platform: any
Classifier: Development Status :: 3 - Alpha
Classifier: License :: OSI Approved :: MIT License
Classifier: Intended Audience :: Science/Research
Classifier: Operating System :: OS Independent
Classifier: Programming Language :: Python
Classifier: Programming Language :: Python :: 2
Classifier: Programming Language :: Python :: 3
Classifier: Topic :: Scientific/Engineering :: Mathematics
Requires-Dist: matplotlib
Requires-Dist: numpy
Requires-Dist: pipdate
